tj_feeder/__init__.py
tj_feeder/batch.py
tj_feeder/configs.py
tj_feeder/time_helper.py
tj_feeder/tj_feed.py
tj_feeder/data/cfg.json
tj_feeder-0.1.0.dist-info/METADATA
tj_feeder-0.1.0.dist-info/WHEEL
tj_feeder-0.1.0.dist-info/entry_points.txt
tj_feeder-0.1.0.dist-info/top_level.txt
tj_feeder-0.1.0.dist-info/RECORD
