Metadata-Version: 2.1
Name: tj-feeder
Version: 0.1.0
Summary: Tool to generate daily input for Task Juggler
Home-page: UNKNOWN
Author: Caio Moraes
Author-email: caiomoraes.cesar@gmail.com
License: UNKNOWN
Platform: UNKNOWN
Classifier: Operating System :: POSIX :: Linux
Classifier: Operating System :: Microsoft :: Windows
Classifier: Programming Language :: Python :: 3
Classifier: Development Status :: 5 - Production/Stable
Requires-Dist: fire (==0.4.0)
Requires-Dist: loguru (==0.5.3)
Requires-Dist: pandas (==1.3.3)
